<?xml version="1.0"?>
<scd version="3">
  <!-- enums -->
  <enum name="calc">
    <value name="Add" id="0x00" />
    <value name="Sub" id="0x01" />
    <value name="Mul" id="0x02" />
    <value name="Div" id="0x03" />
    <value name="Mod" id="0x04" />
    <value name="Or" id="0x05" />
    <value name="And" id="0x06" />
    <value name="Xor" id="0x07" />
    <value name="Not" id="0x08" />
    <value name="Lsl" id="0x09" />
    <value name="Lsr" id="0x0a" />
    <value name="Asr" id="0x0b" />
  </enum>

  <enum name="compare">
    <value name="EQ" id="0x00" />
    <value name="GT" id="0x01" />
    <value name="GE" id="0x02" />
    <value name="LT" id="0x03" />
    <value name="LE" id="0x04" />
    <value name="NE" id="0x05" />
    <value name="??" id="0x06" /><!-- true if (op1 & op2) != 0-->
  </enum>

  <enum name="model">
    <value name="Zombie (Male Civilian)" id="0x10" />
    <value name="Zombie (Female Civilian)" id="0x11" />
    <value name="Zombie (Big Male Civilian)" id="0x12" />
    <value name="Zombie (Female Civilian)" id="0x13" />
    <value name="Zombie (Cop)" id="0x14" />
    <value name="Zombie (Male Civilian)" id="0x15" />
    <value name="Zombie (Male Civilian)" id="0x16" />
    <value name="Zombie (Male Civilian)" id="0x17" />
    <value name="Zombie (Nude)" id="0x18" />
    <value name="Zombie (Worker)" id="0x19" />
    <value name="Zombie (Suit)" id="0x1a" />
    <value name="Zombie (Scientist)" id="0x1b" />
    <value name="Character #2 (Girl)" id="0x1c" />
    <value name="Zombie (Cop)" id="0x1d" />
    <value name="Zombie (Shirt #1)" id="0x1e" />
    <value name="Zombie (Shirt #2)" id="0x1f" />
    <value name="Dog" id="0x20" />
    <value name="Crow" id="0x21" />
    <value name="Hunter" id="0x22" />
    <value name="Chimera" id="0x23" />
    <value name="Hunter (Water)" id="0x24" />
    <value name="Spider (Big)" id="0x25" />
    <value name="Spider (Small)" id="0x26" />
    <value name="Insect (Small)" id="0x27" />
    <value name="Insect (Big)" id="0x28" />
    <value name="Mercenary #1" id="0x2c" />
    <value name="Zombie (Arms)" id="0x2d" />
    <value name="Zombie (Mercenary #1)" id="0x2e" />
    <value name="Marvin Branagh" id="0x2f" />
    <value name="Worm #1 (Big)" id="0x30" />
    <value name="Worm #2 (Small)" id="0x32" />
    <value name="Worm #2 (Big)" id="0x33" />
    <value name="Nemesis #1" id="0x34" />
    <value name="Nemesis #2" id="0x35" />
    <value name="Nemesis #3" id="0x36" />
    <value name="Nemesis #3 (Tentacle)" id="0x37" />
    <value name="Nemesis #4" id="0x38" />
    <value name="Nemesis #4 (Tentacle)" id="0x39" />
    <value name="Nemesis #5" id="0x3a" />
    <value name="Nemesis #5 (Tentacle)" id="0x3b" />
    <value name="Helicopter #1" id="0x3e" />
    <value name="Helicopter #2" id="0x3f" />
    <value name="Plug" id="0x40" />
    <value name="Carlos" id="0x50" />
    <value name="Mercenary #2" id="0x51" />
    <value name="Nicholaï" id="0x52" />
    <value name="Brad Vickers" id="0x53" />
    <value name="Character #1 (Guy)" id="0x54" />
    <value name="Mikhail (Zombie)" id="0x55" />
    <value name="Mercenary #5" id="0x56" />
    <value name="Marvin Branagh" id="0x57" />
    <value name="Brad Vickers (Killed)" id="0x58" />
    <value name="Character #1 (Guy, Killed)" id="0x59" />
    <value name="Character #3 (Girl)" id="0x5a" />
    <value name="Jill Valentine" id="0x5b" />
    <value name="Carlos" id="0x5c" />
    <value name="Carlos" id="0x5d" />
    <value name="Nicholaï" id="0x5e" />
    <value name="Jill Valentine" id="0x5f" />
    <value name="Nicholaï (Killed)" id="0x60" />
    <value name="Character #4 (Girl)" id="0x61" />
    <value name="Jill Valentine (Biker)" id="0x62" />
    <value name="Jill Valentine (Resident Evil)" id="0x63" />
    <value name="Jill Valentine (Disco)" id="0x64" />
    <value name="Jill Valentine (Cop)" id="0x65" />
    <value name="Jill Valentine (Dino Crisis)" id="0x66" />
    <value name="Brian Irons" id="0x67" />
    <value name="Jill Valentine (Black)" id="0x70" />
    <value name="Jill Valentine (Blue)" id="0x71" />
  </enum>

  <enum name="movie">
    <value name="zmovie/ins01.dat" id="0x01" />
    <value name="zmovie/ins02.dat" id="0x02" />
    <value name="zmovie/ins03.dat" id="0x03" />
    <value name="zmovie/ins04.dat" id="0x04" />
    <value name="zmovie/ins05.dat" id="0x05" />
    <value name="zmovie/ins06.dat" id="0x06" />
    <value name="zmovie/ins07.dat" id="0x07" />
  </enum>

  <enum name="workset_object">
    <value name="No_wk" id="0x00" />
    <value name="Pl_wk" id="0x01" />
    <value name="Spl_wk" id="0x02" />
    <value name="Em_wk" id="0x03" />
    <value name="Om_wk" id="0x04" />
    <value name="All_wk" id="0x06" />
    <value name="Pl_parts_wk" id="0x80" />
    <value name="Spl_parts_wk" id="0xa0" />
    <value name="Em_parts_wk" id="0xc0" />
    <value name="Om_parts_wk" id="0xe0" />
  </enum>

  <enum name="aot_type">
    <!-- ptr to this stored in room object list -->
    <value name="dummy" id="0x00" />
    <value name="door" id="0x01" />
    <value name="item" id="0x02" />
    <value name="standard" id="0x03" />
    <value name="message" id="0x04" />
    <value name="event" id="0x05" />
    <value name="flag change" id="0x06" />
    <value name="water" id="0x07" />
    <value name="move" id="0x08" />
    <value name="typewriter" id="0x09" />
    <value name="itembox" id="0x0a" />
    <value name="damage" id="0x0b" />
    <value name="status" id="0x0c" />
    <value name="drawer" id="0x0d" />
    <value name="windows" id="0x0e" />
  </enum>

  <enum name="aot_trigger">
    <value name="disabled" id="0x00" />
    <value name="player \?\?\?" id="0x21" />
    <value name="player activates" id="0x31" />
    <value name="player enters" id="0x41" />
    <value name="*MAYBE* player exits" id="0x42" />
  </enum>

  <!-- Unions -->
  <union name="aot_params">
    <struct name="dummy">
      <field name="unknown" type="Uint16" array="3" />
    </struct>
    <struct name="door" id="0x01">
      <field name="x" type="Sint16" base="10" />
      <field name="y" type="Sint16" base="10" />
      <field name="z" type="Sint16" base="10" />
    </struct>
    <struct name="item" id="0x02">
      <field name="type" type="Uint16" /><!-- enum="item"--> 
      <field name="amount" type="Uint16" base="10" />
      <field name="unknown" type="Uint16" />
    </struct>
    <struct name="standard" id="0x03">
      <field name="unknown" type="Uint16" array="3" />
    </struct>
    <struct name="message" id="0x04">
      <field name="id" type="Uint8" />
      <field name="unknown0" type="Uint8" />
      <field name="unknown1" type="Uint16" array="2" />
    </struct>
    <struct name="event" id="0x05">
      <field name="cond" type="Uint8" />
      <field name="unknown0" type="Uint8" />
      <field name="ex_opcode" type="Uint8"><!-- 2-bytes instruction to execute -->
        <value name="Gosub" id="0x19" />
      </field>
      <field name="event" type="Uint8" />
      <field name="unknown1" type="Uint16" />
    </struct>
    <struct name="flag_change" id="0x06">
      <field name="unknown" type="Uint16" array="3" />
    </struct>
    <struct name="water" id="0x07">
      <field name="unknown" type="Uint16" array="3" />
    </struct>
    <struct name="move" id="0x08">
      <field name="unknown" type="Uint16" array="3" />
    </struct>
    <struct name="typewriter" id="0x09">
      <field name="unknown" type="Uint16" array="3" />
    </struct>
    <struct name="itembox" id="0x0a">
      <field name="unknown" type="Uint16" array="3" />
    </struct>
    <struct name="damage" id="0x0b">
      <field name="unknown" type="Uint16" array="3" />
    </struct>
    <struct name="status" id="0x0c">
      <field name="unknown" type="Uint16" array="3" />
    </struct>
    <struct name="drawer" id="0x0d">
      <field name="unknown" type="Uint16" array="3" />
    </struct>
    <struct name="windows" id="0x0e">
      <field name="unknown" type="Uint16" array="3" />
    </struct>
  </union>

  <!-- 0x00-0x0f --> 
  <inst name="Nop" id="0x00">
    <!-- room101 -->
    <field name="opcode" type="Uint8" />
  </inst>
  <inst name="Evt_end" id="0x01">
    <!-- room100 -->
    <field name="opcode" type="Uint8" />
    <field name="ret_value" type="Uint8" />
  </inst>
  <inst name="Evt_next" id="0x02">
    <!-- room101 -->
    <field name="opcode" type="Uint8" />
  </inst>
  <inst name="Evt_chain" id="0x03">
    <field name="opcode" type="Uint8" />
    <field name="unknown" type="Uint8" />
  </inst>
  <inst name="Evt_exec" id="0x04">
    <!-- room101 -->
    <field name="opcode" type="Uint8" />
    <field name="cond" type="Uint8" />
    <field name="ex_opcode" type="Uint8" >
      <value name="Gosub" id="0x19" />
    </field>
    <field name="event" type="Uint8" />
  </inst>
  <inst name="Evt_kill" id="0x05">
    <!-- room101 -->
    <field name="opcode" type="Uint8" />
    <field name="event" type="Uint8" />
  </inst>
  <inst name="If" id="0x06">
    <!-- room101 -->
    <field name="opcode" type="Uint8" />
    <field name="dummy" type="Uint8" />
    <field name="block_length" type="Uint16" />
  </inst>
  <inst name="Else" id="0x07">
    <!-- room101 -->
    <field name="opcode" type="Uint8" />
    <field name="dummy" type="Uint8" />
    <field name="block_length" type="Uint16" />
  </inst>
  <inst name="Endif" id="0x08">
    <!-- room101 -->
    <field name="opcode" type="Uint8" />
    <field name="dummy" type="Uint8" />
  </inst>
  <inst name="Sleep" id="0x09">
    <!-- room100 -->
    <field name="opcode" type="Uint8" />
  </inst>
  <inst name="Sleeping" id="0x0a">
    <!-- room100 -->
    <field name="opcode" type="Uint8" />
    <field name="delay" type="Uint8" base="10" />
    <field name="unknown" type="Uint8" />
  </inst>
  <inst name="Wsleep" id="0x0b">
    <!-- room101 -->
    <field name="opcode" type="Uint8" />
  </inst>
  <inst name="Wsleeping" id="0x0c">
    <!-- room101 -->
    <field name="opcode" type="Uint8" />
  </inst>
  <inst name="For" id="0x0d">
    <!-- room101 -->
    <field name="opcode" type="Uint8" />
    <field name="dummy" type="Uint8" />
    <field name="block_length" type="Uint16" />
    <field name="count" type="Uint16" base="10" />
  </inst>
  <inst name="0E" id="0x0e">
    <!-- /* continue for, exit for 0x0e ? */ -->
  </inst>
  <inst name="Next" id="0x0f">
    <!-- room101 -->
    <field name="opcode" type="Uint8" />
    <field name="dummy" type="Uint8" />
  </inst>

  <!-- 0x10-0x1f --> 
  <inst name="While" id="0x10">
    <!-- room101 -->
    <field name="opcode" type="Uint8" />
    <field name="dummy" type="Uint8" />
    <field name="block_length" type="Uint16" />
  </inst>
  <inst name="Ewhile" id="0x11">
    <!-- room101 -->
    <field name="opcode" type="Uint8" />
    <field name="dummy" type="Uint8" />
  </inst>
  <inst name="Do" id="0x12">
    <!-- room101 -->
    <field name="opcode" type="Uint8" />
    <field name="dummy" type="Uint8" />
    <field name="block_length" type="Uint16" />
  </inst>
  <inst name="Edwhile" id="0x13">
    <!-- room101 -->
    <field name="opcode" type="Uint8" />
    <field name="dummy" type="Uint8" />
  </inst>
  <inst name="Switch" id="0x14">
    <!-- room101 -->
    <field name="opcode" type="Uint8" />
    <field name="varw" type="Uint8" >
      <value name="CurrentCamera" id="0x1a" />
    </field>
    <field name="block_length" type="Uint16" />
  </inst>
  <inst name="Case" id="0x15">
    <!-- room101 -->
    <field name="opcode" type="Uint8" />
    <field name="dummy" type="Uint8" />
    <field name="block_length" type="Uint16" />
    <field name="value" type="Uint16" base="10" />
  </inst>
  <inst name="Default" id="0x16">
    <!-- room101 -->
    <field name="opcode" type="Uint8" />
    <field name="dummy" type="Uint8" />
  </inst>
  <inst name="Eswitch" id="0x17">
    <!-- room101 -->
    <field name="opcode" type="Uint8" />
    <field name="dummy" type="Uint8" />
  </inst>
  <inst name="Goto" id="0x18">
    <!-- room102 -->
    <field name="opcode" type="Uint8" />
    <field name="unknown0" type="Uint8" />
    <field name="unknown1" type="Uint8" />
    <field name="unknown2" type="Uint8" />
    <field name="rel_offset" type="Sint16" base="10" />
  </inst>
  <inst name="Gosub" id="0x19">
    <!-- room100 -->
    <field name="opcode" type="Uint8" />
    <field name="event" type="Uint8" />
  </inst>
  <inst name="Return" id="0x1a">
    <!-- room504 -->
    <field name="opcode" type="Uint8" />
    <field name="unknown" type="Uint8" array="3" />
  </inst>
  <inst name="Break" id="0x1b">
    <!-- room101 -->
    <field name="opcode" type="Uint8" />
    <field name="dummy" type="Uint8" />
  </inst>
  <inst name="Break_point" id="0x1c">
    <!-- room11c -->
    <field name="opcode" type="Uint8" />
  </inst>
  <inst name="Eval_cc" id="0x1d">
    <!-- room103 -->
    <field name="opcode" type="Uint8" />
    <field name="unknown" type="Uint8" array="3" />
  </inst>
  <inst name="Set1e" id="0x1e">
    <!-- room103 -->
    <field name="opcode" type="Uint8" />
    <field name="unknown" type="Uint8" array="3" />
  </inst>
  <inst name="Set1f" id="0x1f">
    <!-- room103 -->
    <field name="opcode" type="Uint8" />
    <field name="unknown" type="Uint8" array="3" />
  </inst>

  <!-- 0x20-0x2f --> 
  <inst name="Calc" id="0x20">
    <!-- room101 -->
    <field name="opcode" type="Uint8" />
    <field name="dummy" type="Uint8" />
    <field name="operation" type="Uint8" enum="calc" />
    <field name="varw" type="Uint8" />
    <field name="value" type="Uint16" base="10"/>
  </inst>
  <inst name="21" id="0x21">
    <!-- room108 -->
    <field name="opcode" type="Uint8" />
    <field name="unknown" type="Uint8" array="3" />
  </inst>
  <inst name="Evt_cut" id="0x22">
    <!-- room101 -->
    <field name="opcode" type="Uint8" />
    <field name="unknown" type="Uint8" />
    <field name="ex_opcode" type="Uint8" /><!-- 0x19: Gosub -->
    <field name="event" type="Uint8" />
  </inst>
  <inst name="23" id="0x23">
    <field name="opcode" type="Uint8" />
  </inst>
  <inst name="Chaser_evt_clr" id="0x24">
    <!-- room107 -->
    <field name="opcode" type="Uint8" />
    <field name="unknown" type="Uint8" />
  </inst>
  <inst name="Map_open" id="0x25">
    <!-- room502 -->
    <field name="opcode" type="Uint8" />
    <field name="unknown" type="Uint8" array="3" />
  </inst>
  <inst name="Point_add" id="0x26">
    <field name="opcode" type="Uint8" />
    <field name="unknown" type="Uint8" array="5" />
  </inst>
  <inst name="Door_ck" id="0x27">
    <!-- room108 -->
    <field name="opcode" type="Uint8" />
  </inst>
  <inst name="Diedemo_on" id="0x28">
    <!-- room30d -->
    <field name="opcode" type="Uint8" />
  </inst>
  <inst name="Dir_ck" id="0x29">
    <!-- room20c -->
    <field name="opcode" type="Uint8" />
    <field name="unknown" type="Uint8" array="7" />
  </inst>
  <inst name="Parts_set" id="0x2a">
    <!-- room10e -->
    <field name="opcode" type="Uint8" />
    <field name="unknown" type="Uint8" array="5" />
  </inst>
  <inst name="Vloop_set" id="0x2b">
    <!-- room316 -->
    <field name="opcode" type="Uint8" />
    <field name="unknown" type="Uint8" />
  </inst>
  <inst name="Ota_be_set" id="0x2c">
    <!-- room208 -->
    <field name="opcode" type="Uint8" />
    <field name="unknown" type="Uint8" array="3" />
  </inst>
  <inst name="Line_start" id="0x2d">
    <!-- room11b -->
    <field name="opcode" type="Uint8" />
    <field name="unknown" type="Uint8" array="3" />
  </inst>
  <inst name="Line_main" id="0x2e">
    <!-- room11b -->
    <field name="opcode" type="Uint8" />
    <field name="unknown" type="Uint8" array="5" />
  </inst>
  <inst name="Line_end" id="0x2f">
    <!-- room11b -->
    <field name="opcode" type="Uint8" />
    <field name="unknown" type="Uint8" />
  </inst>

  <!-- 0x30-0x3f --> 
  <inst name="Light_pos_set" id="0x30">
    <!-- room10d -->
    <field name="opcode" type="Uint8" />
    <field name="unknown" type="Uint8" array="5" />
  </inst>
  <inst name="Light_kido_set" id="0x31">
    <!-- room217 -->
    <field name="opcode" type="Uint8" />
    <field name="unknown" type="Uint8" array="5" />
  </inst>
  <inst name="Light_color_set" id="0x32">
    <!-- room109 -->
    <field name="opcode" type="Uint8" />
    <field name="id" type="Uint8" />
    <field name="unknown" type="Uint8" />
    <field name="r" type="Uint8" />
    <field name="g" type="Uint8" />
    <field name="b" type="Uint8" />
  </inst>
  <inst name="Ahead_room_set" id="0x33">
    <!-- room107 -->
    <field name="opcode" type="Uint8" />
    <field name="unknown" type="Uint8" array="3" />
  </inst>
  <inst name="Espr_ctr" id="0x34">
    <!-- room50e -->
    <field name="opcode" type="Uint8" />
    <field name="unknown" type="Uint8" array="9" />
  </inst>
  <inst name="Bgm_tbl_ck" id="0x35">
    <!-- room107 -->
    <field name="opcode" type="Uint8" />
    <field name="unknown" type="Uint8" array="5" />
  </inst>
  <inst name="Item_get_ck" id="0x36">
    <!-- room307 -->
    <field name="opcode" type="Uint8" />
    <field name="unknown" type="Uint8" array="2" />
  </inst>
  <inst name="Om_rev" id="0x37">
    <!-- room304 -->
    <field name="opcode" type="Uint8" />
    <field name="unknown" type="Uint8" />
  </inst>
  <inst name="Chaser_life_init" id="0x38">
    <!-- room110 -->
    <field name="opcode" type="Uint8" />
    <field name="unknown" type="Uint8" />
  </inst>
  <inst name="Parts_bomb" id="0x39">
    <!-- room504 -->
    <field name="opcode" type="Uint8" />
    <field name="unknown0" type="Uint8" />
    <field name="unknown1" type="Uint16" array="7" />
  </inst>
  <inst name="Parts_down" id="0x3a">
    <!-- room207 -->
    <field name="opcode" type="Uint8" />
    <field name="unknown0" type="Uint8" />
    <field name="unknown1" type="Uint16" array="7" />
  </inst>
  <inst name="Chaser_item_set" id="0x3b">
    <!-- room107 -->
    <field name="opcode" type="Uint8" />
    <field name="unknown" type="Uint8" array="2" />
  </inst>
  <inst name="Weapon_chg_old" id="0x3c">
    <!-- room201 -->
    <field name="opcode" type="Uint8" />
  </inst>
  <inst name="Sel_evt_on" id="0x3d">
    <!-- room110 -->
    <description>Quick event screen</description>
    <field name="opcode" type="Uint8" />
    <field name="question" type="Uint8">
      <description>Message id of the question the player must answer</description>
    </field>
  </inst>
  <inst name="Item_lost" id="0x3e">
    <!-- room203 -->
    <field name="opcode" type="Uint8" />
    <field name="unknown" type="Uint8" />
  </inst>
  <inst name="Flr_set" id="0x3f">
    <!-- room108 -->
    <field name="opcode" type="Uint8" />
    <field name="unknown" type="Uint8" array="2" />
  </inst>

  <!-- 0x40-0x4f --> 
  <inst name="Memb_set" id="0x40">
    <!-- room101 -->
    <field name="opcode" type="Uint8" />
    <field name="unknown0" type="Uint8" />
    <field name="value" type="Sint16" base="10" />
  </inst>
  <inst name="Memb_set2" id="0x41">
    <!-- room101 -->
    <field name="opcode" type="Uint8" />
    <field name="unknown" type="Uint8" array="2" />
  </inst>
  <inst name="Memb_cpy" id="0x42">
    <!-- room101 -->
    <field name="opcode" type="Uint8" />
    <field name="unknown" type="Uint8" array="2" />
  </inst>
  <inst name="Memb_cmp" id="0x43">
    <!-- room103 -->
    <field name="opcode" type="Uint8" />
    <field name="dummy" type="Uint8" />
    <field name="compare" type="Uint8" enum="compare" />
    <field name="varw" type="Uint8" />
    <field name="value" type="Uint16" base="10"/>
  </inst>
  <inst name="Memb_calc" id="0x44">
    <!-- room20e -->
    <field name="opcode" type="Uint8" />
    <field name="dummy" type="Uint8" />
    <field name="operation" type="Uint8" enum="calc" />
    <field name="varw" type="Uint8" />
    <field name="value" type="Uint16" base="10"/>
  </inst>
  <inst name="Memb_calc2" id="0x45">
    <!-- room200 -->
    <field name="opcode" type="Uint8" />
    <field name="operation" type="Uint8" enum="calc" />
    <field name="varw" type="Uint8" />
    <field name="src" type="Uint8" />
  </inst>
  <inst name="Fade_set" id="0x46">
    <!-- room101 -->
    <field name="opcode" type="Uint8" />
    <field name="unknown" type="Uint8" array="10" />
  </inst>
  <inst name="Work_set" id="0x47">
    <!-- room101 -->
    <field name="opcode" type="Uint8" />
    <field name="unknown" type="Uint8" />
    <field name="object" type="Uint8" enum="workset_object" />
  </inst>
  <inst name="Spd_set" id="0x48">
    <!-- room103 -->
    <field name="opcode" type="Uint8" />
    <field name="unknown" type="Uint8" array="2" />
    <field name="value" type="Sint8" base="10" />
  </inst>
  <inst name="Add_spd" id="0x49">
    <!-- room103 -->
    <field name="opcode" type="Uint8" />
  </inst>
  <inst name="Add_aspd" id="0x4a">
    <!-- room105 -->
    <field name="opcode" type="Uint8" />
  </inst>
  <inst name="Add_vspd" id="0x4b">
    <!-- room20c -->
    <field name="opcode" type="Uint8" />
  </inst>
  <inst name="Ck" id="0x4c">
    <!-- room101 -->
    <field name="opcode" type="Uint8" />
    <field name="unknown" type="Uint8" array="3" />
  </inst>
  <inst name="Set" id="0x4d">
    <!-- room100 -->
    <field name="opcode" type="Uint8" />
    <field name="unknown" type="Uint8" array="3" />
  </inst>
  <inst name="Cmp" id="0x4e">
    <!-- room101 -->
    <field name="opcode" type="Uint8" />
    <field name="unknown" type="Uint8" array="5" />
  </inst>
  <inst name="Rnd" id="0x4f">
    <!-- room10e -->
    <field name="opcode" type="Uint8" />
  </inst>

  <!-- 0x50-0x5f --> 
  <inst name="Cut_chg" id="0x50">
    <!-- room101 -->
    <field name="opcode" type="Uint8" />
    <field name="camera" type="Uint8" />
  </inst>
  <inst name="Cut_old" id="0x51">
    <!-- room103 -->
    <field name="opcode" type="Uint8" />
  </inst>
  <inst name="Cut_auto" id="0x52">
    <!-- room101 -->
    <field name="opcode" type="Uint8" />
    <field name="unknown" type="Uint8" />
  </inst>
  <inst name="Cut_replace" id="0x53">
    <!-- room101 -->
    <field name="opcode" type="Uint8" />
    <field name="camera0" type="Uint8" />
    <field name="camera1" type="Uint8" />
  </inst>
  <inst name="Cut_be_set" id="0x54">
    <!-- room105 -->
    <field name="opcode" type="Uint8" />
    <field name="unknown" type="Uint8" array="3" />
  </inst>
  <inst name="Pos_set" id="0x55">
    <!-- room101 -->
    <field name="opcode" type="Uint8" />
    <field name="dummy" type="Uint8" />
    <field name="x" type="Sint16" base="10" />
    <field name="y" type="Sint16" base="10" />
    <field name="z" type="Sint16" base="10" />
  </inst>
  <inst name="Dir_set" id="0x56">
    <!-- room101 -->
    <field name="opcode" type="Uint8" />
    <field name="unknown" type="Uint8" array="7" />
  </inst>
  <inst name="Set_vib0" id="0x57">
    <!-- room101 -->
    <field name="opcode" type="Uint8" />
    <field name="unknown" type="Uint8" array="5" />
  </inst>
  <inst name="Set_vib1" id="0x58">
    <!-- room103 -->
    <field name="opcode" type="Uint8" />
    <field name="unknown" type="Uint8" array="5" />
  </inst>
  <inst name="Set_vib_fade" id="0x59">
    <!-- room101 -->
    <field name="opcode" type="Uint8" />
    <field name="unknown" type="Uint8" array="7" />
  </inst>
  <inst name="Rbj_set" id="0x5a">
    <!-- room101 -->
    <field name="opcode" type="Uint8" />
    <field name="unknown" type="Uint8" />
  </inst>
  <inst name="Message_on" id="0x5b">
    <!-- room101 -->
    <field name="opcode" type="Uint8" />
    <field name="id" type="Uint8" />
    <field name="unknown" type="Uint16" array="2" />
  </inst>
  <inst name="Rain_set" id="0x5c">
    <!-- room400 -->
    <field name="opcode" type="Uint8" />
    <field name="unknown" type="Uint8" />
  </inst>
  <inst name="Message_off" id="0x5d">
    <!-- room110 -->
    <field name="opcode" type="Uint8" />
  </inst>
  <inst name="Shake_on" id="0x5e">
    <!-- room20c -->
    <field name="opcode" type="Uint8" />
    <field name="unknown" type="Uint8" array="2" />
  </inst>
  <inst name="Weapon_chg" id="0x5f">
    <!-- room201 -->
    <field name="opcode" type="Uint8" />
    <field name="unknown" type="Uint8" />
  </inst>

  <!-- 0x60-0x6f --> 
  <inst name="60" id="0x60">
    <!-- room217 -->
    <field name="opcode" type="Uint8" />
    <field name="unknown0" type="Uint8" />
    <field name="unknown1" type="Uint16" array="10" />
  </inst>
  <inst name="Door_aot_set" id="0x61">
    <!-- room100 -->
    <field name="opcode" type="Uint8" />
    <field name="id" type="Uint8" />
    <field name="unknown0" type="Uint16" array="2" />
    <field name="x" type="Sint16" base="10" />
    <field name="z" type="Sint16" base="10" />
    <field name="w" type="Sint16" base="10" />
    <field name="h" type="Sint16" base="10" />
    <field name="next_x" type="Sint16" base="10" />
    <field name="next_y" type="Sint16" base="10" />
    <field name="next_z" type="Sint16" base="10" />
    <field name="next_dir" type="Sint16" base="10" />
    <field name="next_stage" type="Uint8" />
    <field name="next_room" type="Uint8" />
    <field name="next_camera" type="Uint8" />
    <field name="unknown2" type="Uint8" />
    <field name="door_type" type="Uint8" />
    <field name="door_lock" type="Uint8" />
    <field name="unknown3" type="Uint8" />
    <field name="door_locked" type="Uint8" />
    <field name="door_key" type="Uint8" />
    <field name="unknown4" type="Uint8" />
  </inst>
  <inst name="Door_aot_set_4p" id="0x62">
    <!-- room103 -->
    <field name="opcode" type="Uint8" />
    <field name="id" type="Uint8" />
    <field name="unknown0" type="Uint16" array="2" />
    <field name="x0" type="Sint16" base="10" />
    <field name="z0" type="Sint16" base="10" />
    <field name="x1" type="Sint16" base="10" />
    <field name="z1" type="Sint16" base="10" />
    <field name="x2" type="Sint16" base="10" />
    <field name="z2" type="Sint16" base="10" />
    <field name="x3" type="Sint16" base="10" />
    <field name="z3" type="Sint16" base="10" />   
    <field name="next_x" type="Sint16" base="10" />
    <field name="next_y" type="Sint16" base="10" />
    <field name="next_z" type="Sint16" base="10" />
    <field name="next_dir" type="Sint16" base="10" />
    <field name="next_stage" type="Uint8" />
    <field name="next_room" type="Uint8" />
    <field name="next_camera" type="Uint8" />
    <field name="unknown1" type="Uint8" />
    <field name="unknown2" type="Uint16" array="3" />
  </inst>
  <inst name="Aot_set" id="0x63">
    <!-- room100 -->
    <field name="opcode" type="Uint8" />
    <field name="id" type="Uint8" />
    <field name="unknown0" type="Uint16" array="2" />
    <field name="x" type="Sint16" base="10" />
    <field name="z" type="Sint16" base="10" />
    <field name="w" type="Sint16" base="10" />
    <field name="h" type="Sint16" base="10" />
    <field name="unknown1" type="Uint16" array="3" />
  </inst>
  <inst name="Aot_set_4p" id="0x64">
    <!-- room103 -->
    <field name="opcode" type="Uint8" />
    <field name="id" type="Uint8" />
    <field name="unknown0" type="Uint16" array="2" />
    <field name="x0" type="Sint16" base="10" />
    <field name="z0" type="Sint16" base="10" />
    <field name="x1" type="Sint16" base="10" />
    <field name="z1" type="Sint16" base="10" />
    <field name="x2" type="Sint16" base="10" />
    <field name="z2" type="Sint16" base="10" />
    <field name="x3" type="Sint16" base="10" />
    <field name="z3" type="Sint16" base="10" />   
    <field name="unknown1" type="Uint16" array="3" />
  </inst>
  <inst name="Aot_reset" id="0x65">
    <!-- room101 -->
    <field name="opcode" type="Uint8" />
    <field name="id" type="Uint8" />
    <field name="type" type="Uint8" enum="aot_type" />
    <field name="trigger" type="Uint8" enum="aot_trigger" />
    <field name="aot_params" type="union" switch="type" />
  </inst>
  <inst name="Aot_on" id="0x66">
    <!-- room101 -->
    <field name="opcode" type="Uint8" />
    <field name="id" type="Uint8" />
  </inst>
  <inst name="Item_aot_set" id="0x67">
    <!-- room100 -->
    <field name="opcode" type="Uint8" />
    <field name="unknown0" type="Uint8" />
    <field name="unknown1" type="Uint16" array="2" />
    <field name="x" type="Sint16" base="10" />
    <field name="z" type="Sint16" base="10" />
    <field name="w" type="Sint16" base="10" />
    <field name="h" type="Sint16" base="10" />
    <field name="unknown2" type="Uint16" array="4" />
  </inst>
  <inst name="Item_aot_set_4p" id="0x68">
    <!-- room104 -->
    <field name="opcode" type="Uint8" />
    <field name="unknown0" type="Uint8" />
    <field name="unknown1" type="Uint16" array="14" />
  </inst>
  <inst name="Kage_set" id="0x69">
    <!-- room101 -->
    <field name="opcode" type="Uint8" />
    <field name="unknown0" type="Uint8" />
    <field name="unknown1" type="Uint16" array="6" />
  </inst>
  <inst name="Super_set" id="0x6a">
    <!-- room11b -->
    <field name="opcode" type="Uint8" />
    <field name="unknown0" type="Uint8" />
    <field name="unknown1" type="Uint16" array="7" />
  </inst>
  <inst name="Keep_item_ck" id="0x6b">
    <!-- room111 -->
    <field name="opcode" type="Uint8" />
    <field name="unknown" type="Uint8" />
  </inst>
  <inst name="Key_ck" id="0x6c">
    <!-- room11a -->
    <field name="opcode" type="Uint8" />
    <field name="unknown" type="Uint8" array="3" />
  </inst>
  <inst name="Trg_ck" id="0x6d">
    <!-- room11a -->
    <field name="opcode" type="Uint8" />
    <field name="unknown" type="Uint8" array="3" />
  </inst>
  <inst name="Sca_id_set" id="0x6e">
    <!-- room101 -->
    <field name="opcode" type="Uint8" />
    <field name="unknown" type="Uint8" array="3" />
  </inst>
  <inst name="Om_bomb" id="0x6f">
    <!-- room20b -->
    <field name="opcode" type="Uint8" />
    <field name="unknown" type="Uint8" />
  </inst>

  <!-- 0x70-0x7f --> 
  <inst name="Espr_on" id="0x70">
    <!-- room103 -->
    <field name="opcode" type="Uint8" />
    <field name="unknown0" type="Uint8" />
    <field name="unknown1" type="Uint16" array="3" />
    <field name="x" type="Sint16" base="10" />
    <field name="y" type="Sint16" base="10" />
    <field name="z" type="Sint16" base="10" />
    <field name="unknown2" type="Uint16" />
  </inst>
  <inst name="Espr_on2" id="0x71">
    <!-- room108 -->
    <field name="opcode" type="Uint8" />
    <field name="unknown0" type="Uint8" />
    <field name="unknown1" type="Uint16" array="8" />
  </inst>
  <inst name="Espr3d_on" id="0x72">
    <!-- room101 -->
    <field name="opcode" type="Uint8" />
    <field name="unknown0" type="Uint8" />
    <field name="unknown1" type="Uint16" array="3" />
    <field name="x" type="Sint16" base="10" />
    <field name="y" type="Sint16" base="10" />
    <field name="z" type="Sint16" base="10" />
    <field name="unknown2" type="Uint16" array="4" />
  </inst>
  <inst name="Espr3d_on2" id="0x73">
    <!-- room113 -->
    <field name="opcode" type="Uint8" />
    <field name="dummy" type="Uint8" />
    <field name="id" type="Uint8" />
    <field name="unknown0" type="Uint8" />
    <field name="unknown1" type="Uint16" array="3" />
    <field name="x" type="Sint16" base="10" />
    <field name="y" type="Sint16" base="10" />
    <field name="z" type="Sint16" base="10" />
    <field name="unknown2" type="Uint16" array="4"/>
  </inst>
  <inst name="Espr_kill" id="0x74">
    <!-- room101 -->
    <field name="opcode" type="Uint8" />
    <field name="unknown" type="Uint8" array="4" />
  </inst>
  <inst name="Espr_kill2" id="0x75">
    <!-- room108 -->
    <field name="opcode" type="Uint8" />
    <field name="id" type="Uint8" />
  </inst>
  <inst name="Espr_kill_all" id="0x76">
    <!-- room10d -->
    <field name="opcode" type="Uint8" />
    <field name="unknown" type="Uint8" array="2" />
  </inst>
  <inst name="Se_on" id="0x77">
    <!-- room101 -->
    <field name="opcode" type="Uint8" />
    <field name="unknown0" type="Uint8" />
    <field name="unknown1" type="Uint16" array="5" />
  </inst>
  <inst name="Bgm_ctl" id="0x78">
    <!-- room100 -->
    <field name="opcode" type="Uint8" />
    <field name="unknown" type="Uint8" array="5" />
  </inst>
  <inst name="Xa_on" id="0x79">
    <!-- room101 -->
    <field name="opcode" type="Uint8" />
    <field name="unknown" type="Uint8" array="3" />
  </inst>
  <inst name="Movie_on" id="0x7a">
    <!-- room110 -->
    <field name="opcode" type="Uint8" />
    <field name="id" type="Uint8" enum="movie" />
  </inst>
  <inst name="Bgm_tbl_set" id="0x7b">
    <!-- room101 -->
    <field name="opcode" type="Uint8" />
    <field name="unknown" type="Uint8" array="5" />
  </inst>
  <inst name="Status_on" id="0x7c">
    <!-- room105 -->
    <field name="opcode" type="Uint8" />
  </inst>
  <inst name="Em_set" id="0x7d">
    <!-- room101 -->
    <field name="opcode" type="Uint8" />
    <field name="dummy" type="Uint8" />
    <field name="id" type="Uint8" />
    <field name="model" type="Uint8" enum="model" />
    <field name="unknown1" type="Uint32" array="2" />
    <field name="x" type="Sint16" base="10" />
    <field name="y" type="Sint16" base="10" />
    <field name="z" type="Sint16" base="10" />
    <field name="dir" type="Sint16" base="10" />
    <field name="unknown2" type="Uint16" array="2" />
  </inst>
  <inst name="Mizu_div" id="0x7e">
    <!-- room201 -->
    <field name="opcode" type="Uint8" />
    <field name="unknown" type="Uint8" />
  </inst>
  <inst name="Om_set" id="0x7f">
    <!-- room100 -->
    <field name="opcode" type="Uint8" />
    <field name="unknown0" type="Uint8" />
    <field name="unknown1" type="Uint16" />
    <field name="unknown2" type="Uint32" array="3" />
    <field name="x" type="Sint16" base="10" />
    <field name="y" type="Sint16" base="10" />
    <field name="z" type="Sint16" base="10" />
    <field name="unknown3" type="Uint16" />
    <field name="unknown4" type="Uint32" array="4" />
  </inst>

  <!-- 0x80-0x8f --> 
  <inst name="Plc_motion" id="0x80">
    <!-- room101 -->
    <field name="opcode" type="Uint8" />
    <field name="unknown" type="Uint8" array="3" />
  </inst>
  <inst name="Plc_dest" id="0x81">
    <!-- room101 -->
    <field name="opcode" type="Uint8" />
    <field name="dummy" type="Uint8" />
    <field name="x" type="Sint16" base="10" />
    <field name="y" type="Sint16" base="10" />
    <field name="z" type="Sint16" base="10" />
  </inst>
  <inst name="Plc_neck" id="0x82">
    <!-- room101 -->
    <field name="opcode" type="Uint8" />
    <field name="unknown" type="Uint8" array="9" />
  </inst>
  <inst name="Plc_ret" id="0x83">
    <!-- room101 -->
    <field name="opcode" type="Uint8" />
  </inst>
  <inst name="Plc_flg" id="0x84">
    <!-- room104 -->
    <field name="opcode" type="Uint8" />
    <field name="unknown" type="Uint8" array="3" />
  </inst>
  <inst name="Plc_gun" id="0x85">
    <field name="opcode" type="Uint8" />
    <field name="unknown" type="Uint8" />
  </inst>
  <inst name="Plc_gun_eff" id="0x86">
    <!-- room205, garbage in bytecodes -->
    <field name="opcode" type="Uint8" />
  </inst>
  <inst name="Plc_stop" id="0x87">
    <!-- room101 -->
    <field name="opcode" type="Uint8" />
  </inst>
  <inst name="Plc_rot" id="0x88">
    <!-- room108 -->
    <field name="opcode" type="Uint8" />
    <field name="unknown" type="Uint8" array="3" />
  </inst>
  <inst name="Plc_cnt" id="0x89">
    <!-- room101 -->
    <field name="opcode" type="Uint8" />
    <field name="unknown" type="Uint8" />
  </inst>
  <inst name="Splc_ret" id="0x8a">
    <!-- room107 -->
    <field name="opcode" type="Uint8" />
  </inst>
  <inst name="Splc_sce" id="0x8b">
    <!-- room105 -->
    <field name="opcode" type="Uint8" />
  </inst>
  <inst name="Plc_sce" id="0x8c">
    <!-- room110 -->
    <field name="opcode" type="Uint8" />
  </inst>
  <inst name="Spl_weapon_chg" id="0x8d">
    <!-- room21b -->
    <field name="opcode" type="Uint8" />
  </inst>
  <inst name="Plc_mot_num" id="0x8e">
    <!-- room10d -->
    <field name="opcode" type="Uint8" />
    <field name="unknown" type="Uint8" array="3" />
  </inst>
  <inst name="Em_reset" id="0x8f">
    <!-- room10d -->
    <field name="opcode" type="Uint8" />
    <field name="unknown" type="Uint8" />
  </inst>

</scd>
